pyramid_skosprovider/__init__.py
pyramid_skosprovider/renderers.py
pyramid_skosprovider/utils.py
pyramid_skosprovider/views.py
pyramid_skosprovider-1.3.0.dist-info/METADATA
pyramid_skosprovider-1.3.0.dist-info/WHEEL
pyramid_skosprovider-1.3.0.dist-info/licenses/LICENSE
pyramid_skosprovider-1.3.0.dist-info/RECORD
