Metadata-Version: 2.4
Name: pyramid_skosprovider
Version: 1.3.0
Summary: integration of skosprovider in pyramid
Project-URL: History, https://github.com/OnroerendErfgoed/pyramid_skosprovider/blob/master/HISTORY.rst
Project-URL: Tracker, https://github.com/OnroerendErfgoed/pyramid_skosprovider/issues
Project-URL: Source, https://github.com/OnroerendErfgoed/pyramid_skosprovider
Project-URL: Documentation, https://pyramid-skosprovider.readthedocs.io/en/latest/
Author-email: Flanders Heritage Agency <ict@onroerenderfgoed.be>
License-Expression: MIT
License-File: LICENSE
Keywords: pyramid,skos,skosprovider,thesauri,vocabularies
Classifier: Development Status :: 5 - Production/Stable
Classifier: Framework :: Pyramid
Classifier: Programming Language :: Python
Classifier: Programming Language :: Python :: 3.10
Classifier: Programming Language :: Python :: 3.11
Classifier: Programming Language :: Python :: 3.12
Classifier: Topic :: Internet :: WWW/HTTP
Classifier: Topic :: Internet :: WWW/HTTP :: WSGI :: Application
Requires-Python: <3.13.11,>=3.10
Requires-Dist: pyramid>=2.0.2
Requires-Dist: skosprovider>=1.2.0
Provides-Extra: dev
Requires-Dist: coveralls==4.0.2; extra == 'dev'
Requires-Dist: flake8==7.1.1; extra == 'dev'
Requires-Dist: pygments==2.18.0; extra == 'dev'
Requires-Dist: pytest-cov==5.0.0; extra == 'dev'
Requires-Dist: pytest==8.3.3; extra == 'dev'
Requires-Dist: responses==0.25.3; extra == 'dev'
Requires-Dist: sphinx-rtd-theme==2.0.0; extra == 'dev'
Requires-Dist: sphinx==7.4.7; extra == 'dev'
Requires-Dist: sphinxcontrib-httpdomain==1.8.1; extra == 'dev'
Requires-Dist: uv==0.9.6; extra == 'dev'
Requires-Dist: webtest==3.0.1; extra == 'dev'
